intergalactic/__init__.py
intergalactic/abundances.py
intergalactic/cli.py
intergalactic/constants.py
intergalactic/dtds.py
intergalactic/elements.py
intergalactic/functions.py
intergalactic/imfs.py
intergalactic/matrix.py
intergalactic/model.py
intergalactic/settings.py
intergalactic/sample_input/expelled_elements
intergalactic/sample_input/params.yml
intergalactic-1.2.0.dist-info/LICENSE
intergalactic-1.2.0.dist-info/METADATA
intergalactic-1.2.0.dist-info/WHEEL
intergalactic-1.2.0.dist-info/entry_points.txt
intergalactic-1.2.0.dist-info/top_level.txt
intergalactic-1.2.0.dist-info/RECORD
